capybara/__init__.py
capybara/abst_wrapper.py
capybara/amazon_wrapper.py
capybara/api.py
capybara/capybara.py
capybara/capybaracli.py
capybara/rakuten_wrapper.py
capybara-0.2.0.dist-info/DESCRIPTION.rst
capybara-0.2.0.dist-info/METADATA
capybara-0.2.0.dist-info/metadata.json
capybara-0.2.0.dist-info/RECORD
capybara-0.2.0.dist-info/top_level.txt
capybara-0.2.0.dist-info/WHEEL
capybara-0.2.0.dist-info/zip-safe
