Metadata-Version: 1.1
Name: capybara
Version: 0.2.0
Summary: A simple wrapper for multiple tokens of multiple APIs
Home-page: https://github.com/AkihikoITOH/capybara
Author: ITOH Akihiko
Author-email: akihiko.mus+pypi@gmail.com
License: MIT
Keywords: amazon,product advertising,rakuten,item search,api
Platform: UNKNOWN
Classifier: Development Status :: 3 - Alpha
Classifier: Environment :: Console
Classifier: Intended Audience :: Developers
Classifier: Natural Language :: English
Classifier: Operating System :: OS Independent
Classifier: Programming Language :: Python
Classifier: Topic :: Software Development :: Libraries :: Python Modules
Classifier: Topic :: Internet :: WWW/HTTP :: Dynamic Content :: CGI Tools/Libraries
Classifier: Topic :: Utilities
Classifier: License :: OSI Approved :: MIT License
